{
    "configurations": [
        {
            "name": "Mac",
            "includePath": [
                "${workspaceFolder}/**"
            ],
            "defines": [
                "USE_HAL_DRIVER",
                "STM32F429xx"
            ],
            "macFrameworkPath": [
                "/Library/Developer/CommandLineTools/SDKs/MacOSX.sdk/System/Library/Frameworks"
            ],
            "compilerPath": "/opt/homebrew/bin/arm-none-eabi-gcc",
            "cStandard": "c17",
            "cppStandard": "c++17",
            "intelliSenseMode": "macos-gcc-arm"
        }
    ],
    "version": 4
}